Metadata-Version: 2.4
Name: dask-cudf-cu12
Version: 25.12.0
Summary: Utilities for Dask and cuDF interactions
Author: NVIDIA Corporation
License: Apache-2.0
Project-URL: Homepage, https://github.com/rapidsai/cudf
Classifier: Intended Audience :: Developers
Classifier: Topic :: Database
Classifier: Topic :: Scientific/Engineering
Classifier: License :: OSI Approved :: Apache Software License
Classifier: Programming Language :: Python
Classifier: Programming Language :: Python :: 3.10
Classifier: Programming Language :: Python :: 3.11
Classifier: Programming Language :: Python :: 3.12
Classifier: Programming Language :: Python :: 3.13
Requires-Python: >=3.10
License-File: LICENSE
Requires-Dist: cudf-cu12==25.12.*
Requires-Dist: cupy-cuda12x>=13.6.0
Requires-Dist: fsspec>=0.6.0
Requires-Dist: numpy<3.0a0,>=1.23
Requires-Dist: nvidia-ml-py>=12
Requires-Dist: pandas<2.4.0dev0,>=2.0
Requires-Dist: rapids-dask-dependency==25.12.*
Provides-Extra: test
Requires-Dist: dask-cuda==25.12.*; extra == "test"
Requires-Dist: pytest-cov; extra == "test"
Requires-Dist: pytest-xdist; extra == "test"
Requires-Dist: pytest<9.0.0a0; extra == "test"
Dynamic: license-file
